{"v":"5.12.1","fr":59.9400024414062,"ip":0,"op":420.000017106951,"w":1920,"h":1080,"nm":"Fredchess_Logo_Animation_2","ddd":0,"assets":[],"layers":[{"ddd":0,"ind":1,"ty":4,"nm":"Fredchess Silhouettes 2","sr":1,"ks":{"o":{"a":1,"k":[{"i":{"x":[0.833],"y":[0.833]},"o":{"x":[0.167],"y":[0.167]},"t":228,"s":[0]},{"t":276.00001124171,"s":[100]}],"ix":11},"r":{"a":0,"k":0,"ix":10},"p":{"a":0,"k":[958.6,637.071,0],"ix":2,"l":2},"a":{"a":0,"k":[0,0,0],"ix":1,"l":2},"s":{"a":1,"k":[{"i":{"x":[0.667,0.667,0.667],"y":[1,1,1]},"o":{"x":[0.333,0.333,0.333],"y":[0,0,0]},"t":362,"s":[548.902,760.706,100]},{"t":382.000015559179,"s":[0,0,100]}],"ix":6,"l":2}},"ao":0,"shapes":[{"ty":"gr","it":[{"ind":0,"ty":"sh","ix":1,"ks":{"a":0,"k":{"i":[[0,0],[0,0],[0,0],[0,0],[0,0],[0,0],[0,0],[0,0],[0,0],[0,0]],"o":[[0,0],[0,0],[0,0],[0,0],[0,0],[0,0],[0,0],[0,0],[0,0],[0,0]],"v":[[-93.088,0],[-86.063,0],[-86.063,-10.107],[-76.006,-10.107],[-76.006,-15.768],[-86.063,-15.768],[-86.063,-20.215],[-74.895,-20.215],[-74.895,-25.875],[-93.088,-25.875]],"c":true},"ix":2},"nm":"F","mn":"ADBE Vector Shape - Group","hd":false},{"ty":"st","c":{"a":0,"k":[0.8,0.839215686275,0.964705882353,1],"ix":3},"o":{"a":0,"k":100,"ix":4},"w":{"a":0,"k":1,"ix":5},"lc":1,"lj":1,"ml":4,"bm":0,"nm":"Contour 1","mn":"ADBE Vector Graphic - Stroke","hd":false},{"ty":"fl","c":{"a":0,"k":[0.8,0.839215686275,0.964705882353,1],"ix":4},"o":{"a":0,"k":100,"ix":5},"r":1,"bm":0,"nm":"Fond 1","mn":"ADBE Vector Graphic - Fill","hd":false},{"ty":"tr","p":{"a":0,"k":[0,0],"ix":2},"a":{"a":0,"k":[0,0],"ix":1},"s":{"a":0,"k":[100,100],"ix":3},"r":{"a":0,"k":0,"ix":6},"o":{"a":0,"k":100,"ix":7},"sk":{"a":0,"k":0,"ix":4},"sa":{"a":0,"k":0,"ix":5},"nm":"Transformer "}],"nm":"F","np":3,"cix":2,"bm":0,"ix":1,"mn":"ADBE Vector Group","hd":false},{"ty":"gr","it":[{"ind":0,"ty":"sh","ix":1,"ks":{"a":0,"k":{"i":[[0,0],[0,0],[0,0],[-2.059,0],[-0.695,-0.24],[0,0],[0.606,0],[0.708,-2.729],[0,0],[0,0],[0,0]],"o":[[0,0],[0,0],[0,-2.224],[0.72,0],[0,0],[-0.556,-0.164],[-2.072,0],[0,0],[0,0],[0,0],[0,0]],"v":[[-72.379,0],[-65.405,0],[-65.405,-10.107],[-61.817,-13.797],[-59.239,-13.443],[-59.239,-19.394],[-61.008,-19.659],[-65.405,-15.717],[-65.607,-15.717],[-65.607,-19.406],[-72.379,-19.406]],"c":true},"ix":2},"nm":"r","mn":"ADBE Vector Shape - Group","hd":false},{"ty":"st","c":{"a":0,"k":[0.8,0.839215686275,0.964705882353,1],"ix":3},"o":{"a":0,"k":100,"ix":4},"w":{"a":0,"k":1,"ix":5},"lc":1,"lj":1,"ml":4,"bm":0,"nm":"Contour 1","mn":"ADBE Vector Graphic - Stroke","hd":false},{"ty":"fl","c":{"a":0,"k":[0.8,0.839215686275,0.964705882353,1],"ix":4},"o":{"a":0,"k":100,"ix":5},"r":1,"bm":0,"nm":"Fond 1","mn":"ADBE Vector Graphic - Fill","hd":false},{"ty":"tr","p":{"a":0,"k":[0,0],"ix":2},"a":{"a":0,"k":[0,0],"ix":1},"s":{"a":0,"k":[100,100],"ix":3},"r":{"a":0,"k":0,"ix":6},"o":{"a":0,"k":100,"ix":7},"sk":{"a":0,"k":0,"ix":4},"sa":{"a":0,"k":0,"ix":5},"nm":"Transformer "}],"nm":"r","np":3,"cix":2,"bm":0,"ix":2,"mn":"ADBE Vector Group","hd":false},{"ty":"gr","it":[{"ind":0,"ty":"sh","ix":1,"ks":{"a":0,"k":{"i":[[-6.216,0],[-0.657,4.043],[0,0],[1.428,0],[0,1.87],[0,0],[0,0],[0,0],[5.862,0],[0,-6.014]],"o":[[5.382,0],[0,0],[-0.404,1.099],[-2.072,0],[0,0],[0,0],[0,0],[0,-6.178],[-6.014,0],[0,6.279]],"v":[[-48.608,0.354],[-39.107,-6.267],[-45.475,-6.267],[-48.457,-4.548],[-51.742,-7.783],[-51.742,-8.086],[-39.107,-8.086],[-39.107,-9.703],[-48.76,-19.659],[-58.615,-9.653]],"c":true},"ix":2},"nm":"e","mn":"ADBE Vector Shape - Group","hd":false},{"ind":1,"ty":"sh","ix":2,"ks":{"a":0,"k":{"i":[[0,0],[-1.706,0],[-0.038,-1.668]],"o":[[0.038,-1.68],[1.731,0],[0,0]],"v":[[-51.742,-11.927],[-48.608,-14.757],[-45.526,-11.927]],"c":true},"ix":2},"nm":"e","mn":"ADBE Vector Shape - Group","hd":false},{"ty":"mm","mm":1,"nm":"Fusionner les tracés 1","mn":"ADBE Vector Filter - Merge","hd":false},{"ty":"st","c":{"a":0,"k":[0.8,0.839215686275,0.964705882353,1],"ix":3},"o":{"a":0,"k":100,"ix":4},"w":{"a":0,"k":1,"ix":5},"lc":1,"lj":1,"ml":4,"bm":0,"nm":"Contour 1","mn":"ADBE Vector Graphic - Stroke","hd":false},{"ty":"fl","c":{"a":0,"k":[0.8,0.839215686275,0.964705882353,1],"ix":4},"o":{"a":0,"k":100,"ix":5},"r":1,"bm":0,"nm":"Fond 1","mn":"ADBE Vector Graphic - Fill","hd":false},{"ty":"tr","p":{"a":0,"k":[0,0],"ix":2},"a":{"a":0,"k":[0,0],"ix":1},"s":{"a":0,"k":[100,100],"ix":3},"r":{"a":0,"k":0,"ix":6},"o":{"a":0,"k":100,"ix":7},"sk":{"a":0,"k":0,"ix":4},"sa":{"a":0,"k":0,"ix":5},"nm":"Transformer "}],"nm":"e","np":5,"cix":2,"bm":0,"ix":3,"mn":"ADBE Vector Group","hd":false},{"ty":"gr","it":[{"ind":0,"ty":"sh","ix":1,"ks":{"a":0,"k":{"i":[[-4.144,0],[-0.809,1.971],[0,0],[0,0],[0,0],[0,0],[0,0],[0,0],[0,0],[2.881,0],[0,-7.025]],"o":[[2.729,0],[0,0],[0,0],[0,0],[0,0],[0,0],[0,0],[0,0],[-0.758,-1.971],[-3.841,0],[0,6.721]],"v":[[-28.996,0.253],[-23.589,-3.184],[-23.437,-3.184],[-23.437,0],[-16.514,0],[-16.514,-25.875],[-23.488,-25.875],[-23.488,-16.02],[-23.589,-16.02],[-29.047,-19.659],[-36.627,-9.703]],"c":true},"ix":2},"nm":"d","mn":"ADBE Vector Shape - Group","hd":false},{"ind":1,"ty":"sh","ix":2,"ks":{"a":0,"k":{"i":[[1.92,0],[0,2.881],[-1.92,0],[0,-2.881]],"o":[[-1.92,0],[0,-2.881],[1.92,0],[0,2.83]],"v":[[-26.419,-5.104],[-29.451,-9.703],[-26.419,-14.302],[-23.336,-9.703]],"c":true},"ix":2},"nm":"d","mn":"ADBE Vector Shape - Group","hd":false},{"ty":"mm","mm":1,"nm":"Fusionner les tracés 1","mn":"ADBE Vector Filter - Merge","hd":false},{"ty":"st","c":{"a":0,"k":[0.8,0.839215686275,0.964705882353,1],"ix":3},"o":{"a":0,"k":100,"ix":4},"w":{"a":0,"k":1,"ix":5},"lc":1,"lj":1,"ml":4,"bm":0,"nm":"Contour 1","mn":"ADBE Vector Graphic - Stroke","hd":false},{"ty":"fl","c":{"a":0,"k":[0.8,0.839215686275,0.964705882353,1],"ix":4},"o":{"a":0,"k":100,"ix":5},"r":1,"bm":0,"nm":"Fond 1","mn":"ADBE Vector Graphic - Fill","hd":false},{"ty":"tr","p":{"a":0,"k":[0,0],"ix":2},"a":{"a":0,"k":[0,0],"ix":1},"s":{"a":0,"k":[100,100],"ix":3},"r":{"a":0,"k":0,"ix":6},"o":{"a":0,"k":100,"ix":7},"sk":{"a":0,"k":0,"ix":4},"sa":{"a":0,"k":0,"ix":5},"nm":"Transformer "}],"nm":"d","np":5,"cix":2,"bm":0,"ix":4,"mn":"ADBE Vector Group","hd":false},{"ty":"gr","it":[{"ind":0,"ty":"sh","ix":1,"ks":{"a":0,"k":{"i":[[-6.317,0],[-0.076,5.142],[0,0],[1.529,0],[0,3.184],[-1.832,0],[-0.19,-2.034],[0,0],[5.711,0],[0,-5.963]],"o":[[5.749,0],[0,0],[-0.152,2.034],[-1.832,0],[0,-3.184],[1.541,0],[0,0],[-0.038,-5.054],[-6.317,0],[0,5.963]],"v":[[-3.456,0.354],[5.894,-8.086],[-0.575,-8.086],[-3.355,-4.953],[-6.387,-9.703],[-3.355,-14.454],[-0.575,-11.32],[5.894,-11.32],[-3.456,-19.659],[-13.513,-9.653]],"c":true},"ix":2},"nm":"c","mn":"ADBE Vector Shape - Group","hd":false},{"ty":"st","c":{"a":0,"k":[0.8,0.839215686275,0.964705882353,1],"ix":3},"o":{"a":0,"k":100,"ix":4},"w":{"a":0,"k":1,"ix":5},"lc":1,"lj":1,"ml":4,"bm":0,"nm":"Contour 1","mn":"ADBE Vector Graphic - Stroke","hd":false},{"ty":"fl","c":{"a":0,"k":[0.8,0.839215686275,0.964705882353,1],"ix":4},"o":{"a":0,"k":100,"ix":5},"r":1,"bm":0,"nm":"Fond 1","mn":"ADBE Vector Graphic - Fill","hd":false},{"ty":"tr","p":{"a":0,"k":[0,0],"ix":2},"a":{"a":0,"k":[0,0],"ix":1},"s":{"a":0,"k":[100,100],"ix":3},"r":{"a":0,"k":0,"ix":6},"o":{"a":0,"k":100,"ix":7},"sk":{"a":0,"k":0,"ix":4},"sa":{"a":0,"k":0,"ix":5},"nm":"Transformer "}],"nm":"c","np":3,"cix":2,"bm":0,"ix":5,"mn":"ADBE Vector Group","hd":false},{"ty":"gr","it":[{"ind":0,"ty":"sh","ix":1,"ks":{"a":0,"k":{"i":[[0,0],[-1.706,0],[0.013,-1.92],[0,0],[0,0],[0,0],[4.106,0],[0.872,-2.476],[0,0],[0,0],[0,0],[0,0],[0,0]],"o":[[0.013,-1.92],[1.781,0],[0,0],[0,0],[0,0],[0.013,-4.245],[-2.868,0],[0,0],[0,0],[0,0],[0,0],[0,0],[0,0]],"v":[[16.004,-10.916],[18.834,-13.999],[21.614,-10.916],[21.614,0],[28.588,0],[28.588,-12.382],[21.816,-19.659],[15.954,-15.717],[15.752,-15.717],[15.752,-25.875],[9.03,-25.875],[9.03,0],[16.004,0]],"c":true},"ix":2},"nm":"h","mn":"ADBE Vector Shape - Group","hd":false},{"ty":"st","c":{"a":0,"k":[0.8,0.839215686275,0.964705882353,1],"ix":3},"o":{"a":0,"k":100,"ix":4},"w":{"a":0,"k":1,"ix":5},"lc":1,"lj":1,"ml":4,"bm":0,"nm":"Contour 1","mn":"ADBE Vector Graphic - Stroke","hd":false},{"ty":"fl","c":{"a":0,"k":[0.8,0.839215686275,0.964705882353,1],"ix":4},"o":{"a":0,"k":100,"ix":5},"r":1,"bm":0,"nm":"Fond 1","mn":"ADBE Vector Graphic - Fill","hd":false},{"ty":"tr","p":{"a":0,"k":[0,0],"ix":2},"a":{"a":0,"k":[0,0],"ix":1},"s":{"a":0,"k":[100,100],"ix":3},"r":{"a":0,"k":0,"ix":6},"o":{"a":0,"k":100,"ix":7},"sk":{"a":0,"k":0,"ix":4},"sa":{"a":0,"k":0,"ix":5},"nm":"Transformer "}],"nm":"h","np":3,"cix":2,"bm":0,"ix":6,"mn":"ADBE Vector Group","hd":false},{"ty":"gr","it":[{"ind":0,"ty":"sh","ix":1,"ks":{"a":0,"k":{"i":[[-6.216,0],[-0.657,4.043],[0,0],[1.428,0],[0,1.87],[0,0],[0,0],[0,0],[5.862,0],[0,-6.014]],"o":[[5.382,0],[0,0],[-0.404,1.099],[-2.072,0],[0,0],[0,0],[0,0],[0,-6.178],[-6.014,0],[0,6.279]],"v":[[41.596,0.354],[51.097,-6.267],[44.729,-6.267],[41.748,-4.548],[38.463,-7.783],[38.463,-8.086],[51.097,-8.086],[51.097,-9.703],[41.444,-19.659],[31.59,-9.653]],"c":true},"ix":2},"nm":"e","mn":"ADBE Vector Shape - Group","hd":false},{"ind":1,"ty":"sh","ix":2,"ks":{"a":0,"k":{"i":[[0,0],[-1.706,0],[-0.038,-1.668]],"o":[[0.038,-1.68],[1.731,0],[0,0]],"v":[[38.463,-11.927],[41.596,-14.757],[44.679,-11.927]],"c":true},"ix":2},"nm":"e","mn":"ADBE Vector Shape - Group","hd":false},{"ty":"mm","mm":1,"nm":"Fusionner les tracés 1","mn":"ADBE Vector Filter - Merge","hd":false},{"ty":"st","c":{"a":0,"k":[0.8,0.839215686275,0.964705882353,1],"ix":3},"o":{"a":0,"k":100,"ix":4},"w":{"a":0,"k":1,"ix":5},"lc":1,"lj":1,"ml":4,"bm":0,"nm":"Contour 1","mn":"ADBE Vector Graphic - Stroke","hd":false},{"ty":"fl","c":{"a":0,"k":[0.8,0.839215686275,0.964705882353,1],"ix":4},"o":{"a":0,"k":100,"ix":5},"r":1,"bm":0,"nm":"Fond 1","mn":"ADBE Vector Graphic - Fill","hd":false},{"ty":"tr","p":{"a":0,"k":[0,0],"ix":2},"a":{"a":0,"k":[0,0],"ix":1},"s":{"a":0,"k":[100,100],"ix":3},"r":{"a":0,"k":0,"ix":6},"o":{"a":0,"k":100,"ix":7},"sk":{"a":0,"k":0,"ix":4},"sa":{"a":0,"k":0,"ix":5},"nm":"Transformer "}],"nm":"e","np":5,"cix":2,"bm":0,"ix":7,"mn":"ADBE Vector Group","hd":false},{"ty":"gr","it":[{"ind":0,"ty":"sh","ix":1,"ks":{"a":0,"k":{"i":[[0,0],[5.61,0],[-0.025,-4.043],[-3.955,-0.695],[0,0],[-0.025,-0.733],[1.276,0],[0.19,1.238],[0,0],[-5.938,0],[-0.025,4.157],[3.967,0.72],[0,0],[-0.025,0.569],[-1.2,0],[-0.101,-1.188]],"o":[[-0.177,-4.106],[-5.546,0],[-0.025,3.057],[0,0],[1.516,0.278],[-0.025,0.809],[-1.579,0],[0,0],[0.379,3.98],[5.37,0],[-0.025,-2.868],[0,0],[-1.478,-0.265],[-0.025,-0.809],[1.377,0],[0,0]],"v":[[71.922,-13.089],[62.724,-19.659],[53.779,-13.342],[59.692,-7.631],[63.129,-7.025],[65.352,-5.61],[63.129,-4.346],[60.248,-6.267],[53.325,-6.267],[63.078,0.354],[72.428,-6.418],[66.515,-11.674],[62.573,-12.382],[60.703,-13.746],[62.876,-15.01],[65.504,-13.089]],"c":true},"ix":2},"nm":"s","mn":"ADBE Vector Shape - Group","hd":false},{"ty":"st","c":{"a":0,"k":[0.8,0.839215686275,0.964705882353,1],"ix":3},"o":{"a":0,"k":100,"ix":4},"w":{"a":0,"k":1,"ix":5},"lc":1,"lj":1,"ml":4,"bm":0,"nm":"Contour 1","mn":"ADBE Vector Graphic - Stroke","hd":false},{"ty":"fl","c":{"a":0,"k":[0.8,0.839215686275,0.964705882353,1],"ix":4},"o":{"a":0,"k":100,"ix":5},"r":1,"bm":0,"nm":"Fond 1","mn":"ADBE Vector Graphic - Fill","hd":false},{"ty":"tr","p":{"a":0,"k":[0,0],"ix":2},"a":{"a":0,"k":[0,0],"ix":1},"s":{"a":0,"k":[100,100],"ix":3},"r":{"a":0,"k":0,"ix":6},"o":{"a":0,"k":100,"ix":7},"sk":{"a":0,"k":0,"ix":4},"sa":{"a":0,"k":0,"ix":5},"nm":"Transformer "}],"nm":"s","np":3,"cix":2,"bm":0,"ix":8,"mn":"ADBE Vector Group","hd":false},{"ty":"gr","it":[{"ind":0,"ty":"sh","ix":1,"ks":{"a":0,"k":{"i":[[0,0],[5.61,0],[-0.025,-4.043],[-3.955,-0.695],[0,0],[-0.025,-0.733],[1.276,0],[0.19,1.238],[0,0],[-5.938,0],[-0.025,4.157],[3.967,0.72],[0,0],[-0.025,0.569],[-1.2,0],[-0.101,-1.188]],"o":[[-0.177,-4.106],[-5.546,0],[-0.025,3.057],[0,0],[1.516,0.278],[-0.025,0.809],[-1.579,0],[0,0],[0.379,3.98],[5.37,0],[-0.025,-2.868],[0,0],[-1.478,-0.265],[-0.025,-0.809],[1.377,0],[0,0]],"v":[[93.093,-13.089],[83.895,-19.659],[74.95,-13.342],[80.863,-7.631],[84.299,-7.025],[86.523,-5.61],[84.299,-4.346],[81.419,-6.267],[74.495,-6.267],[84.249,0.354],[93.598,-6.418],[87.685,-11.674],[83.743,-12.382],[81.873,-13.746],[84.046,-15.01],[86.674,-13.089]],"c":true},"ix":2},"nm":"s","mn":"ADBE Vector Shape - Group","hd":false},{"ty":"st","c":{"a":0,"k":[0.8,0.839215686275,0.964705882353,1],"ix":3},"o":{"a":0,"k":100,"ix":4},"w":{"a":0,"k":1,"ix":5},"lc":1,"lj":1,"ml":4,"bm":0,"nm":"Contour 1","mn":"ADBE Vector Graphic - Stroke","hd":false},{"ty":"fl","c":{"a":0,"k":[0.8,0.839215686275,0.964705882353,1],"ix":4},"o":{"a":0,"k":100,"ix":5},"r":1,"bm":0,"nm":"Fond 1","mn":"ADBE Vector Graphic - Fill","hd":false},{"ty":"tr","p":{"a":0,"k":[0,0],"ix":2},"a":{"a":0,"k":[0,0],"ix":1},"s":{"a":0,"k":[100,100],"ix":3},"r":{"a":0,"k":0,"ix":6},"o":{"a":0,"k":100,"ix":7},"sk":{"a":0,"k":0,"ix":4},"sa":{"a":0,"k":0,"ix":5},"nm":"Transformer "}],"nm":"s","np":3,"cix":2,"bm":0,"ix":9,"mn":"ADBE Vector Group","hd":false}],"ip":0,"op":454.000018491799,"st":0,"ct":1,"bm":0},{"ddd":0,"ind":2,"ty":4,"nm":"Calque de forme 1","sr":1,"ks":{"o":{"a":1,"k":[{"i":{"x":[0.667],"y":[1]},"o":{"x":[0.333],"y":[0]},"t":180,"s":[0]},{"t":210.000008553475,"s":[100]}],"ix":11},"r":{"a":0,"k":0,"ix":10},"p":{"a":0,"k":[901,545,0],"ix":2,"l":2},"a":{"a":0,"k":[0,0,0],"ix":1,"l":2},"s":{"a":0,"k":[97.027,100,100],"ix":6,"l":2}},"ao":0,"shapes":[{"ty":"gr","it":[{"d":1,"ty":"el","s":{"a":1,"k":[{"i":{"x":[0.667,0.667],"y":[1,1]},"o":{"x":[0.333,0.333],"y":[0,0]},"t":242,"s":[0,0]},{"t":266.000010834402,"s":[35,35]}],"ix":2},"p":{"a":0,"k":[0,0],"ix":3},"nm":"Tracé d'ellipse 1","mn":"ADBE Vector Shape - Ellipse","hd":false},{"ty":"st","c":{"a":0,"k":[0.392156982422,1,0.854902020623,1],"ix":3},"o":{"a":0,"k":100,"ix":4},"w":{"a":0,"k":1,"ix":5},"lc":1,"lj":1,"ml":4,"bm":0,"nm":"Contour 1","mn":"ADBE Vector Graphic - Stroke","hd":false},{"ty":"fl","c":{"a":0,"k":[0.392156982422,1,0.854902020623,1],"ix":4},"o":{"a":0,"k":100,"ix":5},"r":1,"bm":0,"nm":"Fond 1","mn":"ADBE Vector Graphic - Fill","hd":false},{"ty":"tr","p":{"a":0,"k":[623,75],"ix":2},"a":{"a":0,"k":[0,0],"ix":1},"s":{"a":1,"k":[{"i":{"x":[0.667,0.667],"y":[1,1]},"o":{"x":[0.333,0.333],"y":[0,0]},"t":362,"s":[100,100]},{"t":382.000015559179,"s":[0,0]}],"ix":3},"r":{"a":0,"k":0,"ix":6},"o":{"a":0,"k":100,"ix":7},"sk":{"a":0,"k":0,"ix":4},"sa":{"a":0,"k":0,"ix":5},"nm":"Transformer "}],"nm":"Ellipse 1","np":3,"cix":2,"bm":0,"ix":1,"mn":"ADBE Vector Group","hd":false}],"ip":0,"op":464.000018899107,"st":0,"ct":1,"bm":0},{"ddd":0,"ind":3,"ty":4,"nm":"Fredchess Silhouettes","sr":1,"ks":{"o":{"a":0,"k":100,"ix":11},"r":{"a":0,"k":0,"ix":10},"p":{"a":0,"k":[958.6,637.071,0],"ix":2,"l":2},"a":{"a":0,"k":[0,0,0],"ix":1,"l":2},"s":{"a":0,"k":[548.902,760.706,100],"ix":6,"l":2}},"ao":0,"shapes":[{"ty":"gr","it":[{"ind":0,"ty":"sh","ix":1,"ks":{"a":0,"k":{"i":[[0,0],[0,0],[0,0],[0,0],[0,0],[0,0],[0,0],[0,0],[0,0],[0,0]],"o":[[0,0],[0,0],[0,0],[0,0],[0,0],[0,0],[0,0],[0,0],[0,0],[0,0]],"v":[[-93.088,0],[-86.063,0],[-86.063,-10.107],[-76.006,-10.107],[-76.006,-15.768],[-86.063,-15.768],[-86.063,-20.215],[-74.895,-20.215],[-74.895,-25.875],[-93.088,-25.875]],"c":true},"ix":2},"nm":"F","mn":"ADBE Vector Shape - Group","hd":false},{"ty":"st","c":{"a":0,"k":[0.8,0.839215686275,0.964705882353,1],"ix":3},"o":{"a":0,"k":100,"ix":4},"w":{"a":0,"k":1,"ix":5},"lc":1,"lj":1,"ml":4,"bm":0,"nm":"Contour 1","mn":"ADBE Vector Graphic - Stroke","hd":false},{"ty":"tr","p":{"a":0,"k":[0,0],"ix":2},"a":{"a":0,"k":[0,0],"ix":1},"s":{"a":0,"k":[100,100],"ix":3},"r":{"a":0,"k":0,"ix":6},"o":{"a":0,"k":100,"ix":7},"sk":{"a":0,"k":0,"ix":4},"sa":{"a":0,"k":0,"ix":5},"nm":"Transformer "}],"nm":"F","np":3,"cix":2,"bm":0,"ix":1,"mn":"ADBE Vector Group","hd":false},{"ty":"gr","it":[{"ind":0,"ty":"sh","ix":1,"ks":{"a":0,"k":{"i":[[0,0],[0,0],[0,0],[-2.059,0],[-0.695,-0.24],[0,0],[0.606,0],[0.708,-2.729],[0,0],[0,0],[0,0]],"o":[[0,0],[0,0],[0,-2.224],[0.72,0],[0,0],[-0.556,-0.164],[-2.072,0],[0,0],[0,0],[0,0],[0,0]],"v":[[-72.379,0],[-65.405,0],[-65.405,-10.107],[-61.817,-13.797],[-59.239,-13.443],[-59.239,-19.394],[-61.008,-19.659],[-65.405,-15.717],[-65.607,-15.717],[-65.607,-19.406],[-72.379,-19.406]],"c":true},"ix":2},"nm":"r","mn":"ADBE Vector Shape - Group","hd":false},{"ty":"st","c":{"a":0,"k":[0.8,0.839215686275,0.964705882353,1],"ix":3},"o":{"a":0,"k":100,"ix":4},"w":{"a":0,"k":1,"ix":5},"lc":1,"lj":1,"ml":4,"bm":0,"nm":"Contour 1","mn":"ADBE Vector Graphic - Stroke","hd":false},{"ty":"tr","p":{"a":0,"k":[0,0],"ix":2},"a":{"a":0,"k":[0,0],"ix":1},"s":{"a":0,"k":[100,100],"ix":3},"r":{"a":0,"k":0,"ix":6},"o":{"a":0,"k":100,"ix":7},"sk":{"a":0,"k":0,"ix":4},"sa":{"a":0,"k":0,"ix":5},"nm":"Transformer "}],"nm":"r","np":3,"cix":2,"bm":0,"ix":2,"mn":"ADBE Vector Group","hd":false},{"ty":"gr","it":[{"ind":0,"ty":"sh","ix":1,"ks":{"a":0,"k":{"i":[[-6.216,0],[-0.657,4.043],[0,0],[1.428,0],[0,1.87],[0,0],[0,0],[0,0],[5.862,0],[0,-6.014]],"o":[[5.382,0],[0,0],[-0.404,1.099],[-2.072,0],[0,0],[0,0],[0,0],[0,-6.178],[-6.014,0],[0,6.279]],"v":[[-48.608,0.354],[-39.107,-6.267],[-45.475,-6.267],[-48.457,-4.548],[-51.742,-7.783],[-51.742,-8.086],[-39.107,-8.086],[-39.107,-9.703],[-48.76,-19.659],[-58.615,-9.653]],"c":true},"ix":2},"nm":"e","mn":"ADBE Vector Shape - Group","hd":false},{"ind":1,"ty":"sh","ix":2,"ks":{"a":0,"k":{"i":[[0,0],[-1.706,0],[-0.038,-1.668]],"o":[[0.038,-1.68],[1.731,0],[0,0]],"v":[[-51.742,-11.927],[-48.608,-14.757],[-45.526,-11.927]],"c":true},"ix":2},"nm":"e","mn":"ADBE Vector Shape - Group","hd":false},{"ty":"mm","mm":1,"nm":"Fusionner les tracés 1","mn":"ADBE Vector Filter - Merge","hd":false},{"ty":"st","c":{"a":0,"k":[0.8,0.839215686275,0.964705882353,1],"ix":3},"o":{"a":0,"k":100,"ix":4},"w":{"a":0,"k":1,"ix":5},"lc":1,"lj":1,"ml":4,"bm":0,"nm":"Contour 1","mn":"ADBE Vector Graphic - Stroke","hd":false},{"ty":"tr","p":{"a":0,"k":[0,0],"ix":2},"a":{"a":0,"k":[0,0],"ix":1},"s":{"a":0,"k":[100,100],"ix":3},"r":{"a":0,"k":0,"ix":6},"o":{"a":0,"k":100,"ix":7},"sk":{"a":0,"k":0,"ix":4},"sa":{"a":0,"k":0,"ix":5},"nm":"Transformer "}],"nm":"e","np":5,"cix":2,"bm":0,"ix":3,"mn":"ADBE Vector Group","hd":false},{"ty":"gr","it":[{"ind":0,"ty":"sh","ix":1,"ks":{"a":0,"k":{"i":[[-4.144,0],[-0.809,1.971],[0,0],[0,0],[0,0],[0,0],[0,0],[0,0],[0,0],[2.881,0],[0,-7.025]],"o":[[2.729,0],[0,0],[0,0],[0,0],[0,0],[0,0],[0,0],[0,0],[-0.758,-1.971],[-3.841,0],[0,6.721]],"v":[[-28.996,0.253],[-23.589,-3.184],[-23.437,-3.184],[-23.437,0],[-16.514,0],[-16.514,-25.875],[-23.488,-25.875],[-23.488,-16.02],[-23.589,-16.02],[-29.047,-19.659],[-36.627,-9.703]],"c":true},"ix":2},"nm":"d","mn":"ADBE Vector Shape - Group","hd":false},{"ind":1,"ty":"sh","ix":2,"ks":{"a":0,"k":{"i":[[1.92,0],[0,2.881],[-1.92,0],[0,-2.881]],"o":[[-1.92,0],[0,-2.881],[1.92,0],[0,2.83]],"v":[[-26.419,-5.104],[-29.451,-9.703],[-26.419,-14.302],[-23.336,-9.703]],"c":true},"ix":2},"nm":"d","mn":"ADBE Vector Shape - Group","hd":false},{"ty":"mm","mm":1,"nm":"Fusionner les tracés 1","mn":"ADBE Vector Filter - Merge","hd":false},{"ty":"st","c":{"a":0,"k":[0.8,0.839215686275,0.964705882353,1],"ix":3},"o":{"a":0,"k":100,"ix":4},"w":{"a":0,"k":1,"ix":5},"lc":1,"lj":1,"ml":4,"bm":0,"nm":"Contour 1","mn":"ADBE Vector Graphic - Stroke","hd":false},{"ty":"tr","p":{"a":0,"k":[0,0],"ix":2},"a":{"a":0,"k":[0,0],"ix":1},"s":{"a":0,"k":[100,100],"ix":3},"r":{"a":0,"k":0,"ix":6},"o":{"a":0,"k":100,"ix":7},"sk":{"a":0,"k":0,"ix":4},"sa":{"a":0,"k":0,"ix":5},"nm":"Transformer "}],"nm":"d","np":5,"cix":2,"bm":0,"ix":4,"mn":"ADBE Vector Group","hd":false},{"ty":"gr","it":[{"ind":0,"ty":"sh","ix":1,"ks":{"a":0,"k":{"i":[[-6.317,0],[-0.076,5.142],[0,0],[1.529,0],[0,3.184],[-1.832,0],[-0.19,-2.034],[0,0],[5.711,0],[0,-5.963]],"o":[[5.749,0],[0,0],[-0.152,2.034],[-1.832,0],[0,-3.184],[1.541,0],[0,0],[-0.038,-5.054],[-6.317,0],[0,5.963]],"v":[[-3.456,0.354],[5.894,-8.086],[-0.575,-8.086],[-3.355,-4.953],[-6.387,-9.703],[-3.355,-14.454],[-0.575,-11.32],[5.894,-11.32],[-3.456,-19.659],[-13.513,-9.653]],"c":true},"ix":2},"nm":"c","mn":"ADBE Vector Shape - Group","hd":false},{"ty":"st","c":{"a":0,"k":[0.8,0.839215686275,0.964705882353,1],"ix":3},"o":{"a":0,"k":100,"ix":4},"w":{"a":0,"k":1,"ix":5},"lc":1,"lj":1,"ml":4,"bm":0,"nm":"Contour 1","mn":"ADBE Vector Graphic - Stroke","hd":false},{"ty":"tr","p":{"a":0,"k":[0,0],"ix":2},"a":{"a":0,"k":[0,0],"ix":1},"s":{"a":0,"k":[100,100],"ix":3},"r":{"a":0,"k":0,"ix":6},"o":{"a":0,"k":100,"ix":7},"sk":{"a":0,"k":0,"ix":4},"sa":{"a":0,"k":0,"ix":5},"nm":"Transformer "}],"nm":"c","np":3,"cix":2,"bm":0,"ix":5,"mn":"ADBE Vector Group","hd":false},{"ty":"gr","it":[{"ind":0,"ty":"sh","ix":1,"ks":{"a":0,"k":{"i":[[0,0],[-1.706,0],[0.013,-1.92],[0,0],[0,0],[0,0],[4.106,0],[0.872,-2.476],[0,0],[0,0],[0,0],[0,0],[0,0]],"o":[[0.013,-1.92],[1.781,0],[0,0],[0,0],[0,0],[0.013,-4.245],[-2.868,0],[0,0],[0,0],[0,0],[0,0],[0,0],[0,0]],"v":[[16.004,-10.916],[18.834,-13.999],[21.614,-10.916],[21.614,0],[28.588,0],[28.588,-12.382],[21.816,-19.659],[15.954,-15.717],[15.752,-15.717],[15.752,-25.875],[9.03,-25.875],[9.03,0],[16.004,0]],"c":true},"ix":2},"nm":"h","mn":"ADBE Vector Shape - Group","hd":false},{"ty":"st","c":{"a":0,"k":[0.8,0.839215686275,0.964705882353,1],"ix":3},"o":{"a":0,"k":100,"ix":4},"w":{"a":0,"k":1,"ix":5},"lc":1,"lj":1,"ml":4,"bm":0,"nm":"Contour 1","mn":"ADBE Vector Graphic - Stroke","hd":false},{"ty":"tr","p":{"a":0,"k":[0,0],"ix":2},"a":{"a":0,"k":[0,0],"ix":1},"s":{"a":0,"k":[100,100],"ix":3},"r":{"a":0,"k":0,"ix":6},"o":{"a":0,"k":100,"ix":7},"sk":{"a":0,"k":0,"ix":4},"sa":{"a":0,"k":0,"ix":5},"nm":"Transformer "}],"nm":"h","np":3,"cix":2,"bm":0,"ix":6,"mn":"ADBE Vector Group","hd":false},{"ty":"gr","it":[{"ind":0,"ty":"sh","ix":1,"ks":{"a":0,"k":{"i":[[-6.216,0],[-0.657,4.043],[0,0],[1.428,0],[0,1.87],[0,0],[0,0],[0,0],[5.862,0],[0,-6.014]],"o":[[5.382,0],[0,0],[-0.404,1.099],[-2.072,0],[0,0],[0,0],[0,0],[0,-6.178],[-6.014,0],[0,6.279]],"v":[[41.596,0.354],[51.097,-6.267],[44.729,-6.267],[41.748,-4.548],[38.463,-7.783],[38.463,-8.086],[51.097,-8.086],[51.097,-9.703],[41.444,-19.659],[31.59,-9.653]],"c":true},"ix":2},"nm":"e","mn":"ADBE Vector Shape - Group","hd":false},{"ind":1,"ty":"sh","ix":2,"ks":{"a":0,"k":{"i":[[0,0],[-1.706,0],[-0.038,-1.668]],"o":[[0.038,-1.68],[1.731,0],[0,0]],"v":[[38.463,-11.927],[41.596,-14.757],[44.679,-11.927]],"c":true},"ix":2},"nm":"e","mn":"ADBE Vector Shape - Group","hd":false},{"ty":"mm","mm":1,"nm":"Fusionner les tracés 1","mn":"ADBE Vector Filter - Merge","hd":false},{"ty":"st","c":{"a":0,"k":[0.8,0.839215686275,0.964705882353,1],"ix":3},"o":{"a":0,"k":100,"ix":4},"w":{"a":0,"k":1,"ix":5},"lc":1,"lj":1,"ml":4,"bm":0,"nm":"Contour 1","mn":"ADBE Vector Graphic - Stroke","hd":false},{"ty":"tr","p":{"a":0,"k":[0,0],"ix":2},"a":{"a":0,"k":[0,0],"ix":1},"s":{"a":0,"k":[100,100],"ix":3},"r":{"a":0,"k":0,"ix":6},"o":{"a":0,"k":100,"ix":7},"sk":{"a":0,"k":0,"ix":4},"sa":{"a":0,"k":0,"ix":5},"nm":"Transformer "}],"nm":"e","np":5,"cix":2,"bm":0,"ix":7,"mn":"ADBE Vector Group","hd":false},{"ty":"gr","it":[{"ind":0,"ty":"sh","ix":1,"ks":{"a":0,"k":{"i":[[0,0],[5.61,0],[-0.025,-4.043],[-3.955,-0.695],[0,0],[-0.025,-0.733],[1.276,0],[0.19,1.238],[0,0],[-5.938,0],[-0.025,4.157],[3.967,0.72],[0,0],[-0.025,0.569],[-1.2,0],[-0.101,-1.188]],"o":[[-0.177,-4.106],[-5.546,0],[-0.025,3.057],[0,0],[1.516,0.278],[-0.025,0.809],[-1.579,0],[0,0],[0.379,3.98],[5.37,0],[-0.025,-2.868],[0,0],[-1.478,-0.265],[-0.025,-0.809],[1.377,0],[0,0]],"v":[[71.922,-13.089],[62.724,-19.659],[53.779,-13.342],[59.692,-7.631],[63.129,-7.025],[65.352,-5.61],[63.129,-4.346],[60.248,-6.267],[53.325,-6.267],[63.078,0.354],[72.428,-6.418],[66.515,-11.674],[62.573,-12.382],[60.703,-13.746],[62.876,-15.01],[65.504,-13.089]],"c":true},"ix":2},"nm":"s","mn":"ADBE Vector Shape - Group","hd":false},{"ty":"st","c":{"a":0,"k":[0.8,0.839215686275,0.964705882353,1],"ix":3},"o":{"a":0,"k":100,"ix":4},"w":{"a":0,"k":1,"ix":5},"lc":1,"lj":1,"ml":4,"bm":0,"nm":"Contour 1","mn":"ADBE Vector Graphic - Stroke","hd":false},{"ty":"tr","p":{"a":0,"k":[0,0],"ix":2},"a":{"a":0,"k":[0,0],"ix":1},"s":{"a":0,"k":[100,100],"ix":3},"r":{"a":0,"k":0,"ix":6},"o":{"a":0,"k":100,"ix":7},"sk":{"a":0,"k":0,"ix":4},"sa":{"a":0,"k":0,"ix":5},"nm":"Transformer "}],"nm":"s","np":3,"cix":2,"bm":0,"ix":8,"mn":"ADBE Vector Group","hd":false},{"ty":"gr","it":[{"ind":0,"ty":"sh","ix":1,"ks":{"a":0,"k":{"i":[[0,0],[5.61,0],[-0.025,-4.043],[-3.955,-0.695],[0,0],[-0.025,-0.733],[1.276,0],[0.19,1.238],[0,0],[-5.938,0],[-0.025,4.157],[3.967,0.72],[0,0],[-0.025,0.569],[-1.2,0],[-0.101,-1.188]],"o":[[-0.177,-4.106],[-5.546,0],[-0.025,3.057],[0,0],[1.516,0.278],[-0.025,0.809],[-1.579,0],[0,0],[0.379,3.98],[5.37,0],[-0.025,-2.868],[0,0],[-1.478,-0.265],[-0.025,-0.809],[1.377,0],[0,0]],"v":[[93.093,-13.089],[83.895,-19.659],[74.95,-13.342],[80.863,-7.631],[84.299,-7.025],[86.523,-5.61],[84.299,-4.346],[81.419,-6.267],[74.495,-6.267],[84.249,0.354],[93.598,-6.418],[87.685,-11.674],[83.743,-12.382],[81.873,-13.746],[84.046,-15.01],[86.674,-13.089]],"c":true},"ix":2},"nm":"s","mn":"ADBE Vector Shape - Group","hd":false},{"ty":"st","c":{"a":0,"k":[0.8,0.839215686275,0.964705882353,1],"ix":3},"o":{"a":0,"k":100,"ix":4},"w":{"a":0,"k":1,"ix":5},"lc":1,"lj":1,"ml":4,"bm":0,"nm":"Contour 1","mn":"ADBE Vector Graphic - Stroke","hd":false},{"ty":"tr","p":{"a":0,"k":[0,0],"ix":2},"a":{"a":0,"k":[0,0],"ix":1},"s":{"a":0,"k":[100,100],"ix":3},"r":{"a":0,"k":0,"ix":6},"o":{"a":0,"k":100,"ix":7},"sk":{"a":0,"k":0,"ix":4},"sa":{"a":0,"k":0,"ix":5},"nm":"Transformer "}],"nm":"s","np":3,"cix":2,"bm":0,"ix":9,"mn":"ADBE Vector Group","hd":false},{"ty":"tm","s":{"a":0,"k":0,"ix":1},"e":{"a":1,"k":[{"i":{"x":[0.667],"y":[1]},"o":{"x":[0.333],"y":[0]},"t":0,"s":[0]},{"t":128.055005215787,"s":[100]}],"ix":2},"o":{"a":1,"k":[{"i":{"x":[0.667],"y":[1]},"o":{"x":[0.333],"y":[0]},"t":0,"s":[0]},{"t":128.055005215787,"s":[180]}],"ix":3},"m":1,"ix":10,"nm":"Réduire les tracés 1","mn":"ADBE Vector Filter - Trim","hd":false}],"ip":0,"op":300.00001221925,"st":0,"ct":1,"bm":0}],"markers":[],"props":{}}